visdebug-0.0.1.dist-info/WHEEL
visdebug-0.0.1.dist-info/metadata.json
visdebug-0.0.1.dist-info/METADATA
visdebug-0.0.1.dist-info/top_level.txt
visdebug-0.0.1.dist-info/DESCRIPTION.rst
visdebug-0.0.1.dist-info/RECORD
visdebug/__init__.py
